src/__init__.py
src/__main__.py
src/agent.py
src/cli.py
src/config.yaml
src/db.py
src/export.py
src/prompts.py
src/terminal.py
src/tools.py
src/utils.py
tenk-0.1.2.dist-info/licenses/LICENSE
tenk-0.1.2.dist-info/METADATA
tenk-0.1.2.dist-info/WHEEL
tenk-0.1.2.dist-info/entry_points.txt
tenk-0.1.2.dist-info/top_level.txt
tenk-0.1.2.dist-info/RECORD
