Metadata-Version: 2.4
Name: tenk
Version: 0.1.2
Summary: Talk to SEC filings with AI
Author-email: "Rallies.ai" <support@rallies.ai>
License: Personal Use License
Project-URL: Homepage, https://github.com/rallies-ai/tenk
Project-URL: Documentation, https://github.com/rallies-ai/tenk#readme
Project-URL: Repository, https://github.com/rallies-ai/tenk
Project-URL: Issues, https://github.com/rallies-ai/tenk/issues
Keywords: sec,filings,ai,finance,investing,10-K,10-Q
Classifier: Development Status :: 4 - Beta
Classifier: Intended Audience :: Financial and Insurance Industry
Classifier: License :: Other/Proprietary License
Classifier: Programming Language :: Python :: 3
Classifier: Programming Language :: Python :: 3.10
Classifier: Programming Language :: Python :: 3.11
Classifier: Programming Language :: Python :: 3.12
Classifier: Topic :: Office/Business :: Financial :: Investment
Requires-Python: >=3.10
License-File: LICENSE
Requires-Dist: openai>=1.0.0
Requires-Dist: openai-agents>=0.1.0
Requires-Dist: duckdb>=0.9.0
Requires-Dist: numpy>=1.24.0
Requires-Dist: sentence-transformers>=2.2.0
Requires-Dist: edgartools>=2.0.0
Requires-Dist: yfinance>=0.2.0
Requires-Dist: rich>=13.0.0
Requires-Dist: pyyaml>=6.0
Requires-Dist: markdown>=3.4.0
Requires-Dist: beautifulsoup4>=4.12.0
Requires-Dist: weasyprint>=60.0
Requires-Dist: openpyxl>=3.1.0
Requires-Dist: python-docx>=1.0.0
Provides-Extra: dev
Requires-Dist: pytest>=7.0.0; extra == "dev"
Requires-Dist: black>=23.0.0; extra == "dev"
Requires-Dist: ruff>=0.1.0; extra == "dev"
Dynamic: license-file
